wagtailerrorpages/__init__.py
wagtailerrorpages/static/wagtailerrorpages/main.js
wagtailerrorpages/static/wagtailerrorpages/style.css
wagtailerrorpages/templates/404.html
wagtailerrorpages/templates/500.html
wagtailerrorpages/templates/wagtailerrorpages/404base.html
wagtailerrorpages/templates/wagtailerrorpages/fragments/404message.html
wagtailerrorpages/templatetags/__init__.py
wagtailerrorpages/templatetags/wagtailerrorpages_tags.py
wagtailerrorpages-1.2.1.dist-info/DESCRIPTION.rst
wagtailerrorpages-1.2.1.dist-info/METADATA
wagtailerrorpages-1.2.1.dist-info/RECORD
wagtailerrorpages-1.2.1.dist-info/WHEEL
wagtailerrorpages-1.2.1.dist-info/metadata.json
wagtailerrorpages-1.2.1.dist-info/top_level.txt
