Metadata-Version: 2.0
Name: wagtailerrorpages
Version: 1.2.1
Summary: Pretty, smart, customizable error pages for Wagtail.
Home-page: https://github.com/alexgleason/wagtailerrorpages
Author: Alex Gleason
Author-email: alex@alexgleason.me
License: MIT
Keywords: development
Platform: UNKNOWN
Classifier: Environment :: Web Environment
Classifier: Framework :: Django
Classifier: Intended Audience :: Developers
Classifier: Operating System :: OS Independent
Classifier: Programming Language :: Python
Classifier: Programming Language :: Python :: 3
Classifier: Topic :: Internet :: WWW/HTTP
Classifier: Topic :: Internet :: WWW/HTTP :: Dynamic Content
Requires-Dist: wagtail (>=0.8.7)
Requires-Dist: Django (>=1.7.1)
